{
  "content": [
    {
      "content": null,
      "created": "2025-10-14T12:56:23.637055Z",
      "format": null,
      "hash": null,
      "hash_algorithm": null,
      "last_modified": "2025-10-14T12:52:35.753136Z",
      "mimetype": null,
      "name": "text_utils.ipynb",
      "path": "Day_35_Flask_Web_Framework/app/text_utils.ipynb",
      "size": 2082,
      "type": "notebook",
      "writable": true
    },
    {
      "content": null,
      "created": "2025-10-14T12:56:23.637055Z",
      "format": null,
      "hash": null,
      "hash_algorithm": null,
      "last_modified": "2025-10-14T12:52:35.753136Z",
      "mimetype": "text/x-python",
      "name": "text_utils.py",
      "path": "Day_35_Flask_Web_Framework/app/text_utils.py",
      "size": 1178,
      "type": "file",
      "writable": true
    },
    {
      "content": null,
      "created": "2025-10-14T12:56:23.637055Z",
      "format": null,
      "hash": null,
      "hash_algorithm": null,
      "last_modified": "2025-10-14T12:52:35.753136Z",
      "mimetype": "text/x-python",
      "name": "__main__.py",
      "path": "Day_35_Flask_Web_Framework/app/__main__.py",
      "size": 319,
      "type": "file",
      "writable": true
    },
    {
      "content": null,
      "created": "2025-10-14T12:56:23.636055Z",
      "format": null,
      "hash": null,
      "hash_algorithm": null,
      "last_modified": "2025-10-14T12:52:35.753136Z",
      "mimetype": "text/x-python",
      "name": "__init__.py",
      "path": "Day_35_Flask_Web_Framework/app/__init__.py",
      "size": 2590,
      "type": "file",
      "writable": true
    },
    {
      "content": null,
      "created": "2025-10-14T12:56:23.637055Z",
      "format": null,
      "hash": null,
      "hash_algorithm": null,
      "last_modified": "2025-10-14T12:52:35.753136Z",
      "mimetype": null,
      "name": "__main__.ipynb",
      "path": "Day_35_Flask_Web_Framework/app/__main__.ipynb",
      "size": 936,
      "type": "notebook",
      "writable": true
    }
  ],
  "created": "2025-10-14T12:56:23.637055Z",
  "format": "json",
  "hash": null,
  "hash_algorithm": null,
  "last_modified": "2025-10-14T12:56:23.637055Z",
  "mimetype": null,
  "name": "app",
  "path": "Day_35_Flask_Web_Framework/app",
  "size": null,
  "type": "directory",
  "writable": true
}